plotilleresample
