Metadata-Version: 2.1
Name: plotilleresample
Version: 0.4
Summary: Python3 module to resample datasetsbefore plotting with Plotille.
Home-page: https://github.com/carlosplanchon/plotilleresample
Author: Carlos A. Planchón
Author-email: bubbledoloresuruguay2@gmail.com
License: GPL3
Download-URL: https://github.com/carlosplanchon/plotilleresample/archive/v0.4.tar.gz
Keywords: plotting,ascii,math,resample
Platform: UNKNOWN
Classifier: Intended Audience :: Developers
Classifier: Topic :: Software Development :: Build Tools
Classifier: License :: OSI Approved :: GNU General Public License v3 (GPLv3)
Classifier: Programming Language :: Python :: 3
Classifier: Programming Language :: Python :: 3.4
Classifier: Programming Language :: Python :: 3.5
Classifier: Programming Language :: Python :: 3.6
Classifier: Programming Language :: Python :: 3.7
